nmrwhal/__init__.py
nmrwhal-0.0.2.dist-info/LICENSE
nmrwhal-0.0.2.dist-info/METADATA
nmrwhal-0.0.2.dist-info/WHEEL
nmrwhal-0.0.2.dist-info/top_level.txt
nmrwhal-0.0.2.dist-info/RECORD
