Metadata-Version: 2.1
Name: nmrwhal
Version: 0.0.2
Summary: What is the Fourier Transform of a narwhal?
Home-page: https://github.com/nmrwhal/nmrwhal
Author: nmrwhal developers
Author-email: Joseph.M.Courtney@gmail.com
License: UNKNOWN
Project-URL: Bug Tracker, https://github.com/nmrwhal/nmrwhal/issues
Platform: UNKNOWN
Classifier: Programming Language :: Python :: 3
Classifier: License :: OSI Approved :: MIT License
Classifier: Operating System :: OS Independent
Requires-Python: >=3.6
License-File: LICENSE
